<annotation>
	<folder>점자 블록1</folder>
	<filename>blockImg (345).jpg</filename>
	<path>C:\송이\졸프\점자 블록1\blockImg (345).jpg</path>
	<source>
		<database>Unknown</database>
	</source>
	<size>
		<width>1679</width>
		<height>2751</height>
		<depth>3</depth>
	</size>
	<segmented>0</segmented>
	<object>
		<name>warningBlock</name>
		<pose>Unspecified</pose>
		<truncated>0</truncated>
		<difficult>0</difficult>
		<bndbox>
			<xmin>410</xmin>
			<ymin>1349</ymin>
			<xmax>713</xmax>
			<ymax>1663</ymax>
		</bndbox>
	</object>
	<object>
		<name>warningBlock</name>
		<pose>Unspecified</pose>
		<truncated>0</truncated>
		<difficult>0</difficult>
		<bndbox>
			<xmin>660</xmin>
			<ymin>1507</ymin>
			<xmax>995</xmax>
			<ymax>1778</ymax>
		</bndbox>
	</object>
	<object>
		<name>warningBlock</name>
		<pose>Unspecified</pose>
		<truncated>0</truncated>
		<difficult>0</difficult>
		<bndbox>
			<xmin>954</xmin>
			<ymin>1640</ymin>
			<xmax>1307</xmax>
			<ymax>1943</ymax>
		</bndbox>
	</object>
	<object>
		<name>warningBlock</name>
		<pose>Unspecified</pose>
		<truncated>0</truncated>
		<difficult>0</difficult>
		<bndbox>
			<xmin>1292</xmin>
			<ymin>1772</ymin>
			<xmax>1592</xmax>
			<ymax>2143</ymax>
		</bndbox>
	</object>
	<object>
		<name>warningBlock</name>
		<pose>Unspecified</pose>
		<truncated>1</truncated>
		<difficult>0</difficult>
		<bndbox>
			<xmin>1513</xmin>
			<ymin>1825</ymin>
			<xmax>1679</xmax>
			<ymax>2257</ymax>
		</bndbox>
	</object>
</annotation>
